rotel_sdk/__init__.py
rotel_sdk/open_telemetry/__init__.py
rotel_sdk/open_telemetry/common/__init__.py
rotel_sdk/open_telemetry/common/v1/__init__.pyi
rotel_sdk/open_telemetry/resource/__init__.py
rotel_sdk/open_telemetry/resource/v1/__init__.pyi
rotel_sdk/open_telemetry/trace/__init__.py
rotel_sdk/open_telemetry/trace/v1/__init__.pyi
rotel_sdk-0.0.1.dist-info/METADATA
rotel_sdk-0.0.1.dist-info/WHEEL
rotel_sdk-0.0.1.dist-info/top_level.txt
rotel_sdk-0.0.1.dist-info/RECORD
