Metadata-Version: 2.4
Name: rotel_sdk
Version: 0.0.1
Summary: Rotel SDK for Python Processors
Author-email: Ray Jenkins <ray@streamfold.com>, Michael Heffner <mike@streamfold.com>
License-Expression: MIT
Project-URL: Homepage, https://github.com/streamfold/rotel
Project-URL: Issues, https://github.com/streamfold/rotel/issues
Classifier: Programming Language :: Python :: 3
Classifier: Operating System :: OS Independent
Requires-Python: >=3.9
